LICENCE
README.md
setup.py
motordantic/__init__.py
motordantic/config.py
motordantic/connection.py
motordantic/custom_typing.py
motordantic/document.py
motordantic/exceptions.py
motordantic/manager.py
motordantic/models.py
motordantic/property.py
motordantic/relation.py
motordantic/session.py
motordantic/singleton.py
motordantic/types.py
motordantic/validation.py
motordantic.egg-info/PKG-INFO
motordantic.egg-info/SOURCES.txt
motordantic.egg-info/dependency_links.txt
motordantic.egg-info/requires.txt
motordantic.egg-info/top_level.txt
motordantic/aggregate/__init__.py
motordantic/aggregate/aggregate.py
motordantic/aggregate/expressions.py
motordantic/query/__init__.py
motordantic/query/builder.py
motordantic/query/extra.py
motordantic/query/query.py
motordantic/query/result.py
motordantic/sync/__init__.py
motordantic/sync/query.py
motordantic/sync/sync.py
motordantic/utils/__init__.py
motordantic/utils/pydantic.py
motordantic/utils/typing.py
tests/queries/__init__.py
tests/queries/test_Q.py
tests/queries/test_aggregation.py
tests/queries/test_basic_queries.py
tests/queries/test_indexes.py
tests/queries/test_inner_queries.py
tests/queries/test_raw_queries.py
tests/queries/test_uuid_field.py
tests/queries/test_validation.py
tests/queries/test_write_concern.py