Metadata-Version: 2.1
Name: motordantic
Version: 0.2.1a1
Summary: Mongo ODM, based on motor+pydantic
Home-page: https://github.com/bzdvdn/motordantic
Author: bzdvdn
Author-email: bzdv.dn@gmail.com
License: MIT
Platform: UNKNOWN
Requires-Python: >=3.9
License-File: LICENCE
